trrack_nb_cells/__init__.py
trrack_nb_cells/_version.py
trrack_nb_cells/trrack.py
trrack_nb_cells/labextension/package.json
trrack_nb_cells/labextension/schemas/trrack-nb-cells/package.json.orig
trrack_nb_cells/labextension/schemas/trrack-nb-cells/plugin.json
trrack_nb_cells/labextension/static/568.1552d6e68b2756cecd4c.js
trrack_nb_cells/labextension/static/747.db2c446253a2636d82d8.js
trrack_nb_cells/labextension/static/remoteEntry.5a500b65dddb5f0702b6.js
trrack_nb_cells/labextension/static/style.js
trrack_nb_cells/labextension/static/third-party-licenses.json
trrack_nb_cells-0.1.1.data/data/share/jupyter/labextensions/trrack-nb-cells/package.json
trrack_nb_cells-0.1.1.data/data/share/jupyter/labextensions/trrack-nb-cells/schemas/trrack-nb-cells/package.json.orig
trrack_nb_cells-0.1.1.data/data/share/jupyter/labextensions/trrack-nb-cells/schemas/trrack-nb-cells/plugin.json
trrack_nb_cells-0.1.1.data/data/share/jupyter/labextensions/trrack-nb-cells/static/568.1552d6e68b2756cecd4c.js
trrack_nb_cells-0.1.1.data/data/share/jupyter/labextensions/trrack-nb-cells/static/747.db2c446253a2636d82d8.js
trrack_nb_cells-0.1.1.data/data/share/jupyter/labextensions/trrack-nb-cells/static/remoteEntry.5a500b65dddb5f0702b6.js
trrack_nb_cells-0.1.1.data/data/share/jupyter/labextensions/trrack-nb-cells/static/style.js
trrack_nb_cells-0.1.1.data/data/share/jupyter/labextensions/trrack-nb-cells/static/third-party-licenses.json
trrack_nb_cells-0.1.1.data/data/share/jupyter/labextensions/trrack-nb-cells/install.json
trrack_nb_cells-0.1.1.dist-info/METADATA
trrack_nb_cells-0.1.1.dist-info/WHEEL
trrack_nb_cells-0.1.1.dist-info/licenses/LICENSE
trrack_nb_cells-0.1.1.dist-info/RECORD
