Metadata-Version: 2.1
Name: trrack_nb_cells
Version: 0.1.1
Summary: Extension to track provenance in interactive notebook cells
Project-URL: Homepage,  
Project-URL: Bug Tracker,  /issues
Project-URL: Repository, https://github.com/kirangadhave/notebook-vis-integration
Author-email: Kiran Gadhave <kirangadhave2@gmail.com>
License: BSD 3-Clause License
License-File: LICENSE
Classifier: Framework :: Jupyter
Classifier: Framework :: Jupyter :: JupyterLab
Classifier: Framework :: Jupyter :: JupyterLab :: 3
Classifier: Framework :: Jupyter :: JupyterLab :: Extensions
Classifier: Framework :: Jupyter :: JupyterLab :: Extensions :: Prebuilt
Classifier: License :: OSI Approved :: BSD License
Classifier: Programming Language :: Python
Classifier: Programming Language :: Python :: 3
Classifier: Programming Language :: Python :: 3.7
Classifier: Programming Language :: Python :: 3.8
Classifier: Programming Language :: Python :: 3.9
Classifier: Programming Language :: Python :: 3.10
Classifier: Programming Language :: Python :: 3.11
Requires-Python: >=3.7
Requires-Dist: intent-prediction>=0.1.0
Requires-Dist: reapply>=0.1.0
